{
  "id": 75,
  "colors": [
    [ 18, 17, 10 ],
    [ 6, 6, 4 ],
    [ 18, 13, 9 ],
    [ 23, 18, 12 ],
    [ 27, 22, 14 ],
    [ 0, 0, 0 ],
    [ 0, 0, 0 ],
    [ 28, 21, 19 ],
    [ 0, 0, 0 ],
    [ 0, 0, 0 ],
    [ 0, 0, 0 ],
    [ 0, 0, 0 ],
    [ 0, 0, 0 ],
    [ 0, 0, 0 ],
    [ 0, 0, 0 ],
    [ 0, 0, 0 ]
  ],
  "tiles": [
    {
      "priority": false,
      "collision": 1,
      "h_flippable": true,
      "v_flippable": false,
      "pixels": [
        [ 2, 1, 1, 1, 1, 1, 1, 1 ],
        [ 1, 1, 1, 2, 2, 2, 2, 2 ],
        [ 1, 1, 2, 3, 3, 3, 3, 3 ],
        [ 1, 2, 3, 3, 4, 4, 4, 4 ],
        [ 1, 2, 3, 3, 4, 3, 3, 4 ],
        [ 1, 1, 2, 3, 4, 3, 3, 4 ],
        [ 1, 2, 3, 4, 4, 3, 4, 4 ],
        [ 1, 2, 3, 4, 4, 4, 4, 4 ]
      ]
    },
    {
      "priority": false,
      "collision": 1,
      "h_flippable": false,
      "v_flippable": false,
      "pixels": [
        [ 1, 1, 1, 1, 1, 2, 1, 1 ],
        [ 2, 1, 2, 2, 1, 1, 1, 2 ],
        [ 3, 2, 3, 3, 2, 2, 2, 3 ],
        [ 4, 3, 4, 3, 3, 3, 4, 4 ],
        [ 4, 4, 4, 4, 3, 4, 4, 4 ],
        [ 4, 4, 3, 3, 4, 4, 4, 4 ],
        [ 3, 4, 4, 3, 4, 4, 4, 4 ],
        [ 4, 4, 4, 4, 4, 4, 4, 4 ]
      ]
    },
    {
      "priority": false,
      "collision": 1,
      "h_flippable": true,
      "v_flippable": false,
      "pixels": [
        [ 1, 2, 3, 3, 4, 4, 4, 4 ],
        [ 1, 2, 3, 4, 4, 3, 3, 4 ],
        [ 1, 1, 2, 3, 4, 3, 7, 4 ],
        [ 1, 1, 2, 3, 3, 4, 4, 4 ],
        [ 1, 1, 2, 2, 4, 4, 4, 4 ],
        [ 1, 1, 2, 3, 4, 4, 3, 4 ],
        [ 1, 2, 3, 3, 4, 4, 4, 4 ],
        [ 1, 2, 3, 3, 3, 4, 4, 4 ]
      ]
    },
    {
      "priority": false,
      "collision": 2,
      "h_flippable": true,
      "v_flippable": true,
      "pixels": [
        [ 4, 4, 4, 4, 4, 4, 4, 4 ],
        [ 3, 4, 4, 4, 4, 3, 4, 4 ],
        [ 3, 3, 4, 4, 4, 4, 4, 4 ],
        [ 4, 4, 4, 4, 4, 4, 4, 4 ],
        [ 4, 4, 4, 4, 4, 4, 3, 4 ],
        [ 4, 4, 4, 4, 4, 3, 3, 4 ],
        [ 4, 4, 4, 4, 4, 3, 3, 4 ],
        [ 4, 4, 4, 4, 4, 4, 4, 4 ]
      ]
    },
    {
      "priority": false,
      "collision": 1,
      "h_flippable": true,
      "v_flippable": false,
      "pixels": [
        [ 1, 2, 2, 3, 4, 4, 4, 4 ],
        [ 1, 1, 2, 3, 4, 4, 4, 4 ],
        [ 1, 1, 2, 4, 4, 4, 4, 4 ],
        [ 1, 2, 3, 4, 4, 4, 4, 4 ],
        [ 1, 2, 3, 4, 3, 3, 3, 4 ],
        [ 1, 1, 2, 3, 2, 2, 2, 3 ],
        [ 1, 1, 1, 2, 2, 1, 1, 2 ],
        [ 1, 1, 1, 1, 1, 1, 1, 1 ]
      ]
    },
    {
      "priority": false,
      "collision": 1,
      "h_flippable": false,
      "v_flippable": false,
      "pixels": [
        [ 4, 4, 4, 4, 4, 4, 4, 4 ],
        [ 3, 4, 4, 4, 4, 3, 4, 4 ],
        [ 3, 3, 4, 4, 4, 4, 4, 4 ],
        [ 4, 4, 4, 3, 4, 4, 4, 3 ],
        [ 3, 4, 4, 3, 3, 4, 3, 3 ],
        [ 3, 3, 3, 2, 3, 3, 3, 3 ],
        [ 2, 3, 2, 1, 2, 3, 3, 2 ],
        [ 1, 2, 1, 1, 1, 2, 2, 1 ]
      ]
    },
    {
      "priority": false,
      "collision": 2,
      "h_flippable": true,
      "v_flippable": false,
      "pixels": [
        [ 1, 1, 1, 1, 1, 1, 1, 1 ],
        [ 1, 4, 4, 3, 3, 4, 4, 3 ],
        [ 1, 4, 4, 4, 3, 3, 4, 4 ],
        [ 1, 4, 4, 1, 1, 1, 1, 1 ],
        [ 1, 3, 4, 1, 1, 2, 2, 2 ],
        [ 1, 3, 3, 1, 1, 1, 2, 2 ],
        [ 1, 4, 3, 1, 2, 2, 1, 2 ],
        [ 1, 4, 4, 1, 2, 2, 2, 1 ]
      ]
    },
    {
      "priority": false,
      "collision": 2,
      "h_flippable": true,
      "v_flippable": false,
      "pixels": [
        [ 1, 1, 1, 1, 1, 1, 1, 1 ],
        [ 3, 4, 4, 3, 3, 4, 4, 3 ],
        [ 3, 3, 4, 4, 3, 3, 4, 4 ],
        [ 1, 1, 1, 1, 1, 1, 1, 1 ],
        [ 2, 2, 2, 2, 2, 2, 2, 1 ],
        [ 2, 2, 2, 2, 2, 2, 2, 2 ],
        [ 2, 2, 1, 2, 2, 2, 2, 2 ],
        [ 1, 1, 1, 1, 1, 1, 1, 1 ]
      ]
    },
    {
      "priority": false,
      "collision": 2,
      "h_flippable": true,
      "v_flippable": false,
      "pixels": [
        [ 1, 3, 4, 1, 2, 2, 2, 1 ],
        [ 1, 3, 3, 1, 2, 2, 2, 1 ],
        [ 1, 4, 3, 1, 2, 2, 2, 1 ],
        [ 1, 4, 4, 1, 2, 2, 2, 1 ],
        [ 1, 3, 4, 1, 1, 1, 2, 1 ],
        [ 1, 3, 3, 1, 1, 1, 1, 1 ],
        [ 1, 4, 3, 4, 3, 3, 4, 4 ],
        [ 1, 4, 4, 3, 3, 4, 4, 3 ]
      ]
    },
    {
      "priority": false,
      "collision": 2,
      "h_flippable": true,
      "v_flippable": false,
      "pixels": [
        [ 1, 2, 2, 2, 1, 1, 1, 2 ],
        [ 2, 2, 2, 2, 2, 2, 2, 2 ],
        [ 2, 2, 2, 2, 2, 2, 2, 2 ],
        [ 1, 2, 2, 2, 2, 2, 2, 2 ],
        [ 1, 2, 2, 2, 2, 2, 1, 1 ],
        [ 1, 1, 1, 1, 1, 1, 1, 1 ],
        [ 3, 3, 4, 4, 3, 3, 4, 4 ],
        [ 3, 4, 4, 3, 3, 4, 4, 3 ]
      ]
    },
    {
      "priority": false,
      "collision": 0,
      "h_flippable": false,
      "v_flippable": false,
      "pixels": [
        [ 0, 0, 0, 0, 0, 0, 0, 0 ],
        [ 0, 0, 0, 0, 0, 0, 0, 0 ],
        [ 0, 0, 0, 0, 0, 0, 0, 0 ],
        [ 0, 0, 0, 0, 0, 0, 0, 0 ],
        [ 0, 0, 0, 0, 0, 0, 0, 0 ],
        [ 0, 0, 0, 0, 0, 0, 0, 0 ],
        [ 0, 0, 0, 0, 0, 0, 0, 0 ],
        [ 0, 0, 0, 0, 0, 0, 0, 0 ]
      ]
    },
    {
      "priority": false,
      "collision": 0,
      "h_flippable": false,
      "v_flippable": false,
      "pixels": [
        [ 0, 0, 0, 0, 0, 0, 0, 0 ],
        [ 0, 0, 0, 0, 0, 0, 0, 0 ],
        [ 0, 0, 0, 0, 0, 0, 0, 0 ],
        [ 0, 0, 0, 0, 0, 0, 0, 0 ],
        [ 0, 0, 0, 0, 0, 0, 0, 0 ],
        [ 0, 0, 0, 0, 0, 0, 0, 0 ],
        [ 0, 0, 0, 0, 0, 0, 0, 0 ],
        [ 0, 0, 0, 0, 0, 0, 0, 0 ]
      ]
    },
    {
      "priority": false,
      "collision": 0,
      "h_flippable": false,
      "v_flippable": false,
      "pixels": [
        [ 0, 0, 0, 0, 0, 0, 0, 0 ],
        [ 0, 0, 0, 0, 0, 0, 0, 0 ],
        [ 0, 0, 0, 0, 0, 0, 0, 0 ],
        [ 0, 0, 0, 0, 0, 0, 0, 0 ],
        [ 0, 0, 0, 0, 0, 0, 0, 0 ],
        [ 0, 0, 0, 0, 0, 0, 0, 0 ],
        [ 0, 0, 0, 0, 0, 0, 0, 0 ],
        [ 0, 0, 0, 0, 0, 0, 0, 0 ]
      ]
    },
    {
      "priority": false,
      "collision": 0,
      "h_flippable": false,
      "v_flippable": false,
      "pixels": [
        [ 0, 0, 0, 0, 0, 0, 0, 0 ],
        [ 0, 0, 0, 0, 0, 0, 0, 0 ],
        [ 0, 0, 0, 0, 0, 0, 0, 0 ],
        [ 0, 0, 0, 0, 0, 0, 0, 0 ],
        [ 0, 0, 0, 0, 0, 0, 0, 0 ],
        [ 0, 0, 0, 0, 0, 0, 0, 0 ],
        [ 0, 0, 0, 0, 0, 0, 0, 0 ],
        [ 0, 0, 0, 0, 0, 0, 0, 0 ]
      ]
    },
    {
      "priority": false,
      "collision": 0,
      "h_flippable": false,
      "v_flippable": false,
      "pixels": [
        [ 0, 0, 0, 0, 0, 0, 0, 0 ],
        [ 0, 0, 0, 0, 0, 0, 0, 0 ],
        [ 0, 0, 0, 0, 0, 0, 0, 0 ],
        [ 0, 0, 0, 0, 0, 0, 0, 0 ],
        [ 0, 0, 0, 0, 0, 0, 0, 0 ],
        [ 0, 0, 0, 0, 0, 0, 0, 0 ],
        [ 0, 0, 0, 0, 0, 0, 0, 0 ],
        [ 0, 0, 0, 0, 0, 0, 0, 0 ]
      ]
    },
    {
      "priority": false,
      "collision": 0,
      "h_flippable": false,
      "v_flippable": false,
      "pixels": [
        [ 0, 0, 0, 0, 0, 0, 0, 0 ],
        [ 0, 0, 0, 0, 0, 0, 0, 0 ],
        [ 0, 0, 0, 0, 0, 0, 0, 0 ],
        [ 0, 0, 0, 0, 0, 0, 0, 0 ],
        [ 0, 0, 0, 0, 0, 0, 0, 0 ],
        [ 0, 0, 0, 0, 0, 0, 0, 0 ],
        [ 0, 0, 0, 0, 0, 0, 0, 0 ],
        [ 0, 0, 0, 0, 0, 0, 0, 0 ]
      ]
    }
  ]
}